pyfedwatch/__init__.py
pyfedwatch/datareader.py
pyfedwatch/fedwatch.py
pyfedwatch/fomc.py
pyfedwatch-1.2.0.dist-info/LICENSE
pyfedwatch-1.2.0.dist-info/METADATA
pyfedwatch-1.2.0.dist-info/WHEEL
pyfedwatch-1.2.0.dist-info/top_level.txt
pyfedwatch-1.2.0.dist-info/RECORD
