Metadata-Version: 2.1
Name: pyfedwatch
Version: 1.2.0
Summary: Python Implementation of the CME FedWatch Tool for Estimating Probabilities of Federal Funds Rate Changes at Upcoming FOMC Meetings.
Home-page: https://github.com/ARahimiQuant/pyfedwatch
Author: ALI RAHIMI
Author-email: a.rahimi.aut@gmail.com
License: Apache-2.0
License-File: LICENSE
Requires-Dist: pandas >=2.1.0
Requires-Dist: numpy >=1.25.2
Requires-Dist: python-dateutil >=2.8.2
Requires-Dist: pytz >=2023.3.post1
Requires-Dist: tzdata >=2023.3
Requires-Dist: matplotlib >=3.8.0
Requires-Dist: holidays >=0.32
Requires-Dist: openpyxl >=3.1.2
Requires-Dist: beautifulsoup4 >=4.12.2
Requires-Dist: pandas-datareader ==0.10.0
